{"@t":"2025-11-27T07:29:01.6506375Z","@mt":"HTTP {RequestMethod} {RequestPath} responded {StatusCode} in {Elapsed:0.0000} ms","@r":["10.1078"],"@l":"Error","@x":"System.InvalidOperationException: Testing Serilog exception logging!\r\n   at MovieShopMVC.Controllers.HomeController.TestException() in C:\\Users\\pol\\source\\repos\\MovieShop\\MovieShopMVC\\Controllers\\HomeController.cs:line 26\r\n   at lambda_method185(Closure, Object, Object[])\r\n   at Microsoft.AspNetCore.Mvc.Infrastructure.ActionMethodExecutor.SyncActionResultExecutor.Execute(ActionContext actionContext, IActionResultTypeMapper mapper, ObjectMethodExecutor executor, Object controller, Object[] arguments)\r\n   at Microsoft.AspNetCore.Mvc.Infrastructure.ControllerActionInvoker.InvokeActionMethodAsync()\r\n   at Microsoft.AspNetCore.Mvc.Infrastructure.ControllerActionInvoker.Next(State& next, Scope& scope, Object& state, Boolean& isCompleted)\r\n   at Microsoft.AspNetCore.Mvc.Infrastructure.ControllerActionInvoker.InvokeNextActionFilterAsync()\r\n--- End of stack trace from previous location ---\r\n   at Microsoft.AspNetCore.Mvc.Infrastructure.ControllerActionInvoker.Rethrow(ActionExecutedContextSealed context)\r\n   at Microsoft.AspNetCore.Mvc.Infrastructure.ControllerActionInvoker.Next(State& next, Scope& scope, Object& state, Boolean& isCompleted)\r\n   at Microsoft.AspNetCore.Mvc.Infrastructure.ControllerActionInvoker.InvokeInnerFilterAsync()\r\n--- End of stack trace from previous location ---\r\n   at Microsoft.AspNetCore.Mvc.Infrastructure.ResourceInvoker.<InvokeNextResourceFilter>g__Awaited|25_0(ResourceInvoker invoker, Task lastTask, State next, Scope scope, Object state, Boolean isCompleted)\r\n   at Microsoft.AspNetCore.Mvc.Infrastructure.ResourceInvoker.Rethrow(ResourceExecutedContextSealed context)\r\n   at Microsoft.AspNetCore.Mvc.Infrastructure.ResourceInvoker.Next(State& next, Scope& scope, Object& state, Boolean& isCompleted)\r\n   at Microsoft.AspNetCore.Mvc.Infrastructure.ResourceInvoker.InvokeFilterPipelineAsync()\r\n--- End of stack trace from previous location ---\r\n   at Microsoft.AspNetCore.Mvc.Infrastructure.ResourceInvoker.<InvokeAsync>g__Awaited|17_0(ResourceInvoker invoker, Task task, IDisposable scope)\r\n   at Microsoft.AspNetCore.Mvc.Infrastructure.ResourceInvoker.<InvokeAsync>g__Awaited|17_0(ResourceInvoker invoker, Task task, IDisposable scope)\r\n   at Serilog.AspNetCore.RequestLoggingMiddleware.Invoke(HttpContext httpContext)","@tr":"c3d3a41f290cb3f6019ef782eca9f40b","@sp":"fe7df79fa3d38e59","RequestMethod":"GET","RequestPath":"/Home/TestException","StatusCode":500,"Elapsed":10.1078,"SourceContext":"Serilog.AspNetCore.RequestLoggingMiddleware","ActionId":"532d8ca2-31e9-47db-9bf0-cf0f32e7fc35","ActionName":"MovieShopMVC.Controllers.HomeController.TestException (MovieShopMVC)","RequestId":"0HNHDGQDT47IL:00000017","ConnectionId":"0HNHDGQDT47IL","Application":"MovieShopMVC"}
{"@t":"2025-11-27T07:29:01.7171322Z","@mt":"An unhandled exception has occurred while executing the request.","@l":"Error","@x":"System.InvalidOperationException: Session has not been configured for this application or request.\r\n   at Microsoft.AspNetCore.Http.DefaultHttpContext.get_Session()\r\n   at MovieShopMVC.Middleware.ExceptionHandlingMiddleware.HandleExceptionAsync(HttpContext context, Exception exception) in C:\\Users\\pol\\source\\repos\\MovieShop\\MovieShopMVC\\Middleware\\ExceptionHandlingMiddleware.cs:line 33\r\n   at MovieShopMVC.Middleware.ExceptionHandlingMiddleware.InvokeAsync(HttpContext context) in C:\\Users\\pol\\source\\repos\\MovieShop\\MovieShopMVC\\Middleware\\ExceptionHandlingMiddleware.cs:line 17\r\n   at Microsoft.AspNetCore.Authentication.AuthenticationMiddleware.Invoke(HttpContext context)\r\n   at Microsoft.AspNetCore.Diagnostics.DeveloperExceptionPageMiddlewareImpl.Invoke(HttpContext context)","@tr":"c3d3a41f290cb3f6019ef782eca9f40b","@sp":"fe7df79fa3d38e59","EventId":{"Id":1,"Name":"UnhandledException"},"SourceContext":"Microsoft.AspNetCore.Diagnostics.DeveloperExceptionPageMiddleware","RequestId":"0HNHDGQDT47IL:00000017","RequestPath":"/Home/TestException","ConnectionId":"0HNHDGQDT47IL","Application":"MovieShopMVC"}
